<?xml version="1.0" encoding="UTF-8"?>
  <Document><movie>
    						<title>gran torino</title>
    						<poster>http://www.filmaps.com/posters/0906012453000000</poster>
    						<locations><location>
    											<place>Grosse Pointe Park, Michigan, USA</place>
    										<scene></scene>
        									<coordinates>-82.9287,42.3784</coordinates>
        									</location><location>
    											<place>15020 Kercheval Ave., Grosse Pte Park, MI 48230</place>
    										<scene>Pointe Hardware Co - where Walt and Thao shop for tools</scene>
        									<coordinates>-82.923,42.3869</coordinates>
        									</location><location>
    											<place>15020 Hampton St., Grosse Pointe Park, MI 48230</place>
    										<scene>St Ambrose Church - funeral and church scenes</scene>
        									<coordinates>-82.9386,42.3762</coordinates>
        									</location></locations>
						</movie><movie>
    						<title>gran torino</title>
    						<poster>http://www.filmaps.com/posters/0906012453000000</poster>
    						<locations><location>
    											<place>Grosse Pointe Park, Michigan, USA</place>
    										<scene></scene>
        									<coordinates>-82.9287,42.3784</coordinates>
        									</location><location>
    											<place>15020 Kercheval Ave., Grosse Pte Park, MI 48230</place>
    										<scene>Pointe Hardware Co - where Walt and Thao shop for tools</scene>
        									<coordinates>-82.923,42.3869</coordinates>
        									</location><location>
    											<place>15020 Hampton St., Grosse Pointe Park, MI 48230</place>
    										<scene>St Ambrose Church - funeral and church scenes</scene>
        									<coordinates>-82.9386,42.3762</coordinates>
        									</location></locations>
						</movie><movie>
    						<title>gran torino</title>
    						<poster>http://www.filmaps.com/posters/0906012453000000</poster>
    						<locations><location>
    											<place>Grosse Pointe Park, Michigan, USA</place>
    										<scene></scene>
        									<coordinates>-82.9287,42.3784</coordinates>
        									</location><location>
    											<place>15020 Kercheval Ave., Grosse Pte Park, MI 48230</place>
    										<scene>Pointe Hardware Co - where Walt and Thao shop for tools</scene>
        									<coordinates>-82.923,42.3869</coordinates>
        									</location><location>
    											<place>15020 Hampton St., Grosse Pointe Park, MI 48230</place>
    										<scene>St Ambrose Church - funeral and church scenes</scene>
        									<coordinates>-82.9386,42.3762</coordinates>
        									</location></locations>
						</movie></Document>