<?xml version="1.0" encoding="UTF-8"?>
  <Document><movie>
    						<title>Lethal Weapon</title>
    						<poster>http://www.filmaps.com/posters/0901201555000000</poster>
    						<locations><location>
    											<place>700 E. Ocean Boulevard, Long Beach, California, USA</place>
    										<scene>opening scene in the International Tower</scene>
        									<coordinates>-118.184,33.7659</coordinates>
        									</location></locations>
						</movie><movie>
    						<title>the aviator</title>
    						<poster>http://www.filmaps.com/posters/0902254152000000</poster>
    						<locations><location>
    											<place>72nd Place, Long Beach, California, USA</place>
    										<scene>Hughes comes ashore to meet Hepburn</scene>
        									<coordinates>-118.117,33.7454</coordinates>
        									</location></locations>
						</movie><movie>
    						<title>A Cinderella Story</title>
    						<poster>http://www.filmaps.com/posters/0902275228000000</poster>
    						<locations><location>
    											<place>4390 Atlantic Avenue, Long Beach</place>
    										<scene>George's 50's Diner</scene>
        									<coordinates>-118.185,33.8367</coordinates>
        									</location></locations>
						</movie><movie>
    						<title>Coyote Bar</title>
    						<poster>http://www.filmaps.com/posters/0903283208000000</poster>
    						<locations><location>
    											<place>Atlantic Beach, Long Island, New York</place>
    										<scene></scene>
        									<coordinates>-73.6567,40.5919</coordinates>
        									</location></locations>
						</movie><movie>
    						<title>Speed</title>
    						<poster>http://www.filmaps.com/posters/0905311613000000</poster>
    						<locations><location>
    											<place>Ocean Boulevard, Long Beach, California, USA</place>
    										<scene>street scenes</scene>
        									<coordinates>-118.22,33.7651</coordinates>
        									</location></locations>
						</movie><movie>
    						<title>Thelma and Louise</title>
    						<poster>http://www.filmaps.com/posters/0906133934000000</poster>
    						<locations><location>
    											<place>3321 South St., Long Beach, California</place>
    										<scene> Cowboy Country bar was the mid-west C&amp;W bar where the attempted rape that turns the adventure take palce here.</scene>
        									<coordinates>-118.152,33.8606</coordinates>
        									</location><location>
    											<place>long beach</place>
    										<scene>saloon i aparcament primera nit</scene>
        									<coordinates>-118.189,33.7671</coordinates>
        									</location></locations>
						</movie><movie>
    						<title>Ferris Bueller's Day Off</title>
    						<poster>http://www.filmaps.com/posters/0908072532000000</poster>
    						<locations><location>
    											<place>4160 Country Club Drive, Long Beach, California, USA</place>
    										<scene>Bueller home, exterior</scene>
        									<coordinates>-118.199,33.8315</coordinates>
        									</location></locations>
						</movie><movie>
    						<title>Rush Hour 3</title>
    						<poster>http://www.filmaps.com/posters/0908154324000000</poster>
    						<locations><location>
    											<place>Long Beach, California, USA</place>
    										<scene></scene>
        									<coordinates>-118.162,33.762</coordinates>
        									</location><location>
    											<place>1050 Linden Avenue, Long Beach, California, USA</place>
    										<scene>Hospital scene</scene>
        									<coordinates>-118.186,33.7801</coordinates>
        									</location></locations>
						</movie><movie>
    						<title>Rush Hour 3</title>
    						<poster>http://www.filmaps.com/posters/0908154324000000</poster>
    						<locations><location>
    											<place>Long Beach, California, USA</place>
    										<scene></scene>
        									<coordinates>-118.162,33.762</coordinates>
        									</location><location>
    											<place>1050 Linden Avenue, Long Beach, California, USA</place>
    										<scene>Hospital scene</scene>
        									<coordinates>-118.186,33.7801</coordinates>
        									</location></locations>
						</movie><movie>
    						<title>American Pie 2</title>
    						<poster>http://www.filmaps.com/posters/0909083230000000</poster>
    						<locations><location>
    											<place>4165 Country Club Drive, Los Cerritos, Long Beach, Ca</place>
    										<scene>house was used in a variety of scenes, where Finch and Stiffler talked about how tantra sexual rites can improve Stiffler's sex life</scene>
        									<coordinates>-118.199,33.8318</coordinates>
        									</location></locations>
						</movie><movie>
    						<title>Donnie Darko</title>
    						<poster>http://www.filmaps.com/posters/0909080748000000</poster>
    						<locations><location>
    											<place>Long Beach, California, USA</place>
    										<scene></scene>
        									<coordinates>-118.152,33.7899</coordinates>
        									</location><location>
    											<place>4225 Country Club Drive, Los Cerritos, CA</place>
    										<scene>fictional family home for the teenager Donnie Darko</scene>
        									<coordinates>-118.199,33.8341</coordinates>
        									</location></locations>
						</movie><movie>
    						<title>Donnie Darko</title>
    						<poster>http://www.filmaps.com/posters/0909080748000000</poster>
    						<locations><location>
    											<place>Long Beach, California, USA</place>
    										<scene></scene>
        									<coordinates>-118.152,33.7899</coordinates>
        									</location><location>
    											<place>4225 Country Club Drive, Los Cerritos, CA</place>
    										<scene>fictional family home for the teenager Donnie Darko</scene>
        									<coordinates>-118.199,33.8341</coordinates>
        									</location></locations>
						</movie><movie>
    						<title>American Pie</title>
    						<poster>http://www.filmaps.com/posters/0909083425000000</poster>
    						<locations><location>
    											<place>3925 Cedar Drive, Los Cerritos, Long Beach, CA</place>
    										<scene>The house served as the family home of Alyson Hannigan's character Michelle Flaherty</scene>
        									<coordinates>-118.197,33.8294</coordinates>
        									</location><location>
    											<place>4153 Cedar Drive, Long Beach, California</place>
    										<scene>The main house in American Pie (1999), home to Jim and his family</scene>
        									<coordinates>-118.197,33.8315</coordinates>
        									</location></locations>
						</movie><movie>
    						<title>All About Steve</title>
    						<poster>http://www.filmaps.com/posters/0909105614000000</poster>
    						<locations><location>
    											<place>110 w 6th st long beach ca</place>
    										<scene>apt building she walked past to mail "steve" puzzle</scene>
        									<coordinates>-118.193,33.7744</coordinates>
        									</location><location>
    											<place>Press Telegram, 602 Pine Ave, Long Beach, CA,USA</place>
    										<scene>Mary Horowitz talks to her editor.</scene>
        									<coordinates>-118.192,33.7743</coordinates>
        									</location></locations>
						</movie><movie>
    						<title>American Pie</title>
    						<poster>http://www.filmaps.com/posters/0909083425000000</poster>
    						<locations><location>
    											<place>3925 Cedar Drive, Los Cerritos, Long Beach, CA</place>
    										<scene>The house served as the family home of Alyson Hannigan's character Michelle Flaherty</scene>
        									<coordinates>-118.197,33.8294</coordinates>
        									</location><location>
    											<place>4153 Cedar Drive, Long Beach, California</place>
    										<scene>The main house in American Pie (1999), home to Jim and his family</scene>
        									<coordinates>-118.197,33.8315</coordinates>
        									</location></locations>
						</movie><movie>
    						<title>dexter</title>
    						<poster>http://www.filmaps.com/posters/0904203005000000</poster>
    						<locations><location>
    											<place>Colorado Lagoon Park, Long Beach, Los Angeles</place>
    										<scene>Park where they find Miguel's body</scene>
        									<coordinates>-118.134,33.7717</coordinates>
        									</location><location>
    											<place>3827 N. Weston Place, Long Beach, CA</place>
    										<scene>Miguel Prado's House</scene>
        									<coordinates>-118.193,33.8275</coordinates>
        									</location><location>
    											<place>4020 E. Olympic Plaza, Long Beach, CA, USA</place>
    										<scene>Beach Patio Cafe</scene>
        									<coordinates>-118.146,33.7585</coordinates>
        									</location><location>
    											<place>3333 E 1st St, Long Beach, CA, United States</place>
    										<scene>Dexter Season 4 House</scene>
        									<coordinates>-118.153,33.7626</coordinates>
        									</location><location>
    											<place>3331 E 1st St, Long Beach, CA, United States</place>
    										<scene>Dester Season 4 House</scene>
        									<coordinates>-118.153,33.7626</coordinates>
        									</location><location>
    											<place>Shoreline Village, Long Beach, CA, USA</place>
    										<scene>The Ice Truck Killer leaves a surprise in Santa's Village</scene>
        									<coordinates>-118.192,33.7603</coordinates>
        									</location></locations>
						</movie><movie>
    						<title>dexter</title>
    						<poster>http://www.filmaps.com/posters/0904203005000000</poster>
    						<locations><location>
    											<place>Colorado Lagoon Park, Long Beach, Los Angeles</place>
    										<scene>Park where they find Miguel's body</scene>
        									<coordinates>-118.134,33.7717</coordinates>
        									</location><location>
    											<place>3827 N. Weston Place, Long Beach, CA</place>
    										<scene>Miguel Prado's House</scene>
        									<coordinates>-118.193,33.8275</coordinates>
        									</location><location>
    											<place>4020 E. Olympic Plaza, Long Beach, CA, USA</place>
    										<scene>Beach Patio Cafe</scene>
        									<coordinates>-118.146,33.7585</coordinates>
        									</location><location>
    											<place>3333 E 1st St, Long Beach, CA, United States</place>
    										<scene>Dexter Season 4 House</scene>
        									<coordinates>-118.153,33.7626</coordinates>
        									</location><location>
    											<place>3331 E 1st St, Long Beach, CA, United States</place>
    										<scene>Dester Season 4 House</scene>
        									<coordinates>-118.153,33.7626</coordinates>
        									</location><location>
    											<place>Shoreline Village, Long Beach, CA, USA</place>
    										<scene>The Ice Truck Killer leaves a surprise in Santa's Village</scene>
        									<coordinates>-118.192,33.7603</coordinates>
        									</location></locations>
						</movie><movie>
    						<title>dexter</title>
    						<poster>http://www.filmaps.com/posters/0904203005000000</poster>
    						<locations><location>
    											<place>Colorado Lagoon Park, Long Beach, Los Angeles</place>
    										<scene>Park where they find Miguel's body</scene>
        									<coordinates>-118.134,33.7717</coordinates>
        									</location><location>
    											<place>3827 N. Weston Place, Long Beach, CA</place>
    										<scene>Miguel Prado's House</scene>
        									<coordinates>-118.193,33.8275</coordinates>
        									</location><location>
    											<place>4020 E. Olympic Plaza, Long Beach, CA, USA</place>
    										<scene>Beach Patio Cafe</scene>
        									<coordinates>-118.146,33.7585</coordinates>
        									</location><location>
    											<place>3333 E 1st St, Long Beach, CA, United States</place>
    										<scene>Dexter Season 4 House</scene>
        									<coordinates>-118.153,33.7626</coordinates>
        									</location><location>
    											<place>3331 E 1st St, Long Beach, CA, United States</place>
    										<scene>Dester Season 4 House</scene>
        									<coordinates>-118.153,33.7626</coordinates>
        									</location><location>
    											<place>Shoreline Village, Long Beach, CA, USA</place>
    										<scene>The Ice Truck Killer leaves a surprise in Santa's Village</scene>
        									<coordinates>-118.192,33.7603</coordinates>
        									</location></locations>
						</movie><movie>
    						<title>Qué Les Pasa A Los Hombres</title>
    						<poster>http://www.filmaps.com/posters/0909140813000000</poster>
    						<locations><location>
    											<place>1126 Queens Highway, Long Beach, California, USA</place>
    										<scene></scene>
        									<coordinates>-118.19,33.7524</coordinates>
        									</location></locations>
						</movie><movie>
    						<title>dexter</title>
    						<poster>http://www.filmaps.com/posters/0904203005000000</poster>
    						<locations><location>
    											<place>Colorado Lagoon Park, Long Beach, Los Angeles</place>
    										<scene>Park where they find Miguel's body</scene>
        									<coordinates>-118.134,33.7717</coordinates>
        									</location><location>
    											<place>3827 N. Weston Place, Long Beach, CA</place>
    										<scene>Miguel Prado's House</scene>
        									<coordinates>-118.193,33.8275</coordinates>
        									</location><location>
    											<place>4020 E. Olympic Plaza, Long Beach, CA, USA</place>
    										<scene>Beach Patio Cafe</scene>
        									<coordinates>-118.146,33.7585</coordinates>
        									</location><location>
    											<place>3333 E 1st St, Long Beach, CA, United States</place>
    										<scene>Dexter Season 4 House</scene>
        									<coordinates>-118.153,33.7626</coordinates>
        									</location><location>
    											<place>3331 E 1st St, Long Beach, CA, United States</place>
    										<scene>Dester Season 4 House</scene>
        									<coordinates>-118.153,33.7626</coordinates>
        									</location><location>
    											<place>Shoreline Village, Long Beach, CA, USA</place>
    										<scene>The Ice Truck Killer leaves a surprise in Santa's Village</scene>
        									<coordinates>-118.192,33.7603</coordinates>
        									</location></locations>
						</movie><movie>
    						<title>dexter</title>
    						<poster>http://www.filmaps.com/posters/0904203005000000</poster>
    						<locations><location>
    											<place>Colorado Lagoon Park, Long Beach, Los Angeles</place>
    										<scene>Park where they find Miguel's body</scene>
        									<coordinates>-118.134,33.7717</coordinates>
        									</location><location>
    											<place>3827 N. Weston Place, Long Beach, CA</place>
    										<scene>Miguel Prado's House</scene>
        									<coordinates>-118.193,33.8275</coordinates>
        									</location><location>
    											<place>4020 E. Olympic Plaza, Long Beach, CA, USA</place>
    										<scene>Beach Patio Cafe</scene>
        									<coordinates>-118.146,33.7585</coordinates>
        									</location><location>
    											<place>3333 E 1st St, Long Beach, CA, United States</place>
    										<scene>Dexter Season 4 House</scene>
        									<coordinates>-118.153,33.7626</coordinates>
        									</location><location>
    											<place>3331 E 1st St, Long Beach, CA, United States</place>
    										<scene>Dester Season 4 House</scene>
        									<coordinates>-118.153,33.7626</coordinates>
        									</location><location>
    											<place>Shoreline Village, Long Beach, CA, USA</place>
    										<scene>The Ice Truck Killer leaves a surprise in Santa's Village</scene>
        									<coordinates>-118.192,33.7603</coordinates>
        									</location></locations>
						</movie><movie>
    						<title>what lies beneath</title>
    						<poster>http://www.filmaps.com/posters/0904060729000000</poster>
    						<locations><location>
    											<place>1126 Queens Highway, Long Beach, California, USA</place>
    										<scene></scene>
        									<coordinates>-118.19,33.7528</coordinates>
        									</location></locations>
						</movie><movie>
    						<title>as good as it gets</title>
    						<poster>http://www.filmaps.com/posters/1001080019000000</poster>
    						<locations><location>
    											<place>110 N. Marina Drive, Long Beach, California, USA</place>
    										<scene>Baltimore Restaurant</scene>
        									<coordinates>-118.113,33.7484</coordinates>
        									</location></locations>
						</movie><movie>
    						<title>Bones</title>
    						<poster>http://www.filmaps.com/posters/1001182545000000</poster>
    						<locations><location>
    											<place>Press Telegram, 602 Pine Ave., Long Beach, CA, USA</place>
    										<scene>body found in a trunk in an alley</scene>
        									<coordinates>-118.193,33.7744</coordinates>
        									</location></locations>
						</movie><movie>
    						<title>CSI Miami</title>
    						<poster>http://www.filmaps.com/posters/1001192205000000</poster>
    						<locations><location>
    											<place>110 Oceangate, Long Beach, CA, USA</place>
    										<scene>stunt at the parking garage</scene>
        									<coordinates>-118.199,33.7662</coordinates>
        									</location></locations>
						</movie><movie>
    						<title>All About Steve</title>
    						<poster>http://www.filmaps.com/posters/0909105614000000</poster>
    						<locations><location>
    											<place>110 w 6th st long beach ca</place>
    										<scene>apt building she walked past to mail "steve" puzzle</scene>
        									<coordinates>-118.193,33.7744</coordinates>
        									</location><location>
    											<place>Press Telegram, 602 Pine Ave, Long Beach, CA,USA</place>
    										<scene>Mary Horowitz talks to her editor.</scene>
        									<coordinates>-118.192,33.7743</coordinates>
        									</location></locations>
						</movie><movie>
    						<title>dexter</title>
    						<poster>http://www.filmaps.com/posters/0904203005000000</poster>
    						<locations><location>
    											<place>Colorado Lagoon Park, Long Beach, Los Angeles</place>
    										<scene>Park where they find Miguel's body</scene>
        									<coordinates>-118.134,33.7717</coordinates>
        									</location><location>
    											<place>3827 N. Weston Place, Long Beach, CA</place>
    										<scene>Miguel Prado's House</scene>
        									<coordinates>-118.193,33.8275</coordinates>
        									</location><location>
    											<place>4020 E. Olympic Plaza, Long Beach, CA, USA</place>
    										<scene>Beach Patio Cafe</scene>
        									<coordinates>-118.146,33.7585</coordinates>
        									</location><location>
    											<place>3333 E 1st St, Long Beach, CA, United States</place>
    										<scene>Dexter Season 4 House</scene>
        									<coordinates>-118.153,33.7626</coordinates>
        									</location><location>
    											<place>3331 E 1st St, Long Beach, CA, United States</place>
    										<scene>Dester Season 4 House</scene>
        									<coordinates>-118.153,33.7626</coordinates>
        									</location><location>
    											<place>Shoreline Village, Long Beach, CA, USA</place>
    										<scene>The Ice Truck Killer leaves a surprise in Santa's Village</scene>
        									<coordinates>-118.192,33.7603</coordinates>
        									</location></locations>
						</movie><movie>
    						<title>Coach Carter</title>
    						<poster>http://www.filmaps.com/posters/1001184753000000</poster>
    						<locations><location>
    											<place>St. Anthony's High School, 620 Olive Ave., Long Beach, CA, USA</place>
    										<scene>numerous basketball scenes, locker room scenes</scene>
        									<coordinates>-118.181,33.7738</coordinates>
        									</location></locations>
						</movie><movie>
    						<title>The Longest Yard</title>
    						<poster>http://www.filmaps.com/posters/1001185052000000</poster>
    						<locations><location>
    											<place>St. Anthonys High School, 620 Olive Ave., Long Beach, CA, USA</place>
    										<scene>Locker rooms scenes</scene>
        									<coordinates>-118.181,33.7738</coordinates>
        									</location><location>
    											<place>Long Beach, California, USA</place>
    										<scene>Car chase scene</scene>
        									<coordinates>-118.18,33.7632</coordinates>
        									</location><location>
    											<place>National Guard Armory, 854 7th Street, Long Beach, CA, USA</place>
    										<scene>Ping pong scene</scene>
        									<coordinates>-118.181,33.7752</coordinates>
        									</location></locations>
						</movie><movie>
    						<title>Cinderella Story</title>
    						<poster>http://www.filmaps.com/posters/1001181020000000</poster>
    						<locations><location>
    											<place>George's Diner, 4390 Atlantic Ave., Long Beach, CA, USA</place>
    										<scene>Flashback and modern times</scene>
        									<coordinates>-118.185,33.8364</coordinates>
        									</location></locations>
						</movie><movie>
    						<title>The Longest Yard</title>
    						<poster>http://www.filmaps.com/posters/1001185052000000</poster>
    						<locations><location>
    											<place>St. Anthonys High School, 620 Olive Ave., Long Beach, CA, USA</place>
    										<scene>Locker rooms scenes</scene>
        									<coordinates>-118.181,33.7738</coordinates>
        									</location><location>
    											<place>Long Beach, California, USA</place>
    										<scene>Car chase scene</scene>
        									<coordinates>-118.18,33.7632</coordinates>
        									</location><location>
    											<place>National Guard Armory, 854 7th Street, Long Beach, CA, USA</place>
    										<scene>Ping pong scene</scene>
        									<coordinates>-118.181,33.7752</coordinates>
        									</location></locations>
						</movie><movie>
    						<title>Liscense to Wed</title>
    						<poster>http://www.filmaps.com/posters/1001211518000000</poster>
    						<locations><location>
    											<place>First Congragational Church, 241 Cedar Ave, Long Beach, CA, USA</place>
    										<scene>Wedding rehearsal scene</scene>
        									<coordinates>-118.196,33.7702</coordinates>
        									</location><location>
    											<place>The Willmore, 315 West 3rd Street, Long Beach, CA, USA</place>
    										<scene>A mural was painted on the wall to create "Chicago" hoop shooting scene</scene>
        									<coordinates>-118.195,33.7705</coordinates>
        									</location></locations>
						</movie><movie>
    						<title>The Longest Yard</title>
    						<poster>http://www.filmaps.com/posters/1001185052000000</poster>
    						<locations><location>
    											<place>St. Anthonys High School, 620 Olive Ave., Long Beach, CA, USA</place>
    										<scene>Locker rooms scenes</scene>
        									<coordinates>-118.181,33.7738</coordinates>
        									</location><location>
    											<place>Long Beach, California, USA</place>
    										<scene>Car chase scene</scene>
        									<coordinates>-118.18,33.7632</coordinates>
        									</location><location>
    											<place>National Guard Armory, 854 7th Street, Long Beach, CA, USA</place>
    										<scene>Ping pong scene</scene>
        									<coordinates>-118.181,33.7752</coordinates>
        									</location></locations>
						</movie><movie>
    						<title>Liscense to Wed</title>
    						<poster>http://www.filmaps.com/posters/1001211518000000</poster>
    						<locations><location>
    											<place>First Congragational Church, 241 Cedar Ave, Long Beach, CA, USA</place>
    										<scene>Wedding rehearsal scene</scene>
        									<coordinates>-118.196,33.7702</coordinates>
        									</location><location>
    											<place>The Willmore, 315 West 3rd Street, Long Beach, CA, USA</place>
    										<scene>A mural was painted on the wall to create "Chicago" hoop shooting scene</scene>
        									<coordinates>-118.195,33.7705</coordinates>
        									</location></locations>
						</movie><movie>
    						<title>Boston Legal</title>
    						<poster>http://www.filmaps.com/posters/1001213559000000</poster>
    						<locations><location>
    											<place>California Apartments, 325 West Third St, Long Beach, CA USA</place>
    										<scene>a sidewalk stroll in the last episode</scene>
        									<coordinates>-118.196,33.7708</coordinates>
        									</location></locations>
						</movie><movie>
    						<title>The Girl Next Door</title>
    						<poster>http://www.filmaps.com/posters/1001213814000000</poster>
    						<locations><location>
    											<place>4100 Block Country Club Dr., Long Beach, CA, USA</place>
    										<scene>swimming pools, streaking scene</scene>
        									<coordinates>-118.198,33.8245</coordinates>
        									</location></locations>
						</movie><movie>
    						<title>Red Dragon</title>
    						<poster>http://www.filmaps.com/posters/1002063017000000</poster>
    						<locations><location>
    											<place>4100 block Country Club Drive, Long Beach CA USA</place>
    										<scene>opening scenes</scene>
        									<coordinates>-118.198,33.825</coordinates>
        									</location></locations>
						</movie><movie>
    						<title>Fractured</title>
    						<poster>http://www.filmaps.com/posters/</poster>
    						<locations><location>
    											<place>Hangar, 2845 Spring St., Long Beach CA</place>
    										<scene>Opening scene--plane crash investigation</scene>
        									<coordinates>-118.158,33.8116</coordinates>
        									</location></locations>
						</movie><movie>
    						<title>Anger Management</title>
    						<poster>http://www.filmaps.com/posters/1003041021000000</poster>
    						<locations><location>
    											<place>Bayshore &amp; 64th Place, Long Beach, CA</place>
    										<scene>date scene gone wrong between Adam Sandler &amp; Heather Graham</scene>
        									<coordinates>-118.121,33.7491</coordinates>
        									</location></locations>
						</movie><movie>
    						<title>There Will Be Blood</title>
    						<poster>http://www.filmaps.com/posters/1003023056000000</poster>
    						<locations><location>
    											<place>Spring &amp; Orange, Long Beach, CA</place>
    										<scene>Daniel Day-Lewis stakes his oil claim</scene>
        									<coordinates>-118.177,33.8113</coordinates>
        									</location></locations>
						</movie><movie>
    						<title>Thelma and Louise</title>
    						<poster>http://www.filmaps.com/posters/0906133934000000</poster>
    						<locations><location>
    											<place>3321 South St., Long Beach, California</place>
    										<scene> Cowboy Country bar was the mid-west C&amp;W bar where the attempted rape that turns the adventure take palce here.</scene>
        									<coordinates>-118.152,33.8606</coordinates>
        									</location><location>
    											<place>long beach</place>
    										<scene>saloon i aparcament primera nit</scene>
        									<coordinates>-118.189,33.7671</coordinates>
        									</location></locations>
						</movie><movie>
    						<title>Inception</title>
    						<poster>http://www.filmaps.com/posters/1007223648000000</poster>
    						<locations><location>
    											<place>Henry Ford Bridge, Los Angeles, CA</place>
    										<scene>Van falls from the bridge scene</scene>
        									<coordinates>-118.24,33.7659</coordinates>
        									</location></locations>
						</movie></Document>
