<?xml version="1.0" encoding="UTF-8"?>
  <Document><movie>
    						<title>Villa Amalia</title>
    						<poster>http://www.filmaps.com/posters/0906120637000000</poster>
    						<locations><location>
    											<place>Monte Epomeo, Serrara Fontana (Isola d'Ischia, Napoli)</place>
    										<scene>Ann is in the top of the highest mountain of the island.</scene>
        									<coordinates>13.8964,40.7312</coordinates>
        									</location></locations>
						</movie></Document>